README.md
setup.cfg
setup.py
wwpdb/__init__.py
wwpdb.apps.entity_transform.egg-info/PKG-INFO
wwpdb.apps.entity_transform.egg-info/SOURCES.txt
wwpdb.apps.entity_transform.egg-info/dependency_links.txt
wwpdb.apps.entity_transform.egg-info/not-zip-safe
wwpdb.apps.entity_transform.egg-info/requires.txt
wwpdb.apps.entity_transform.egg-info/top_level.txt
wwpdb/apps/__init__.py
wwpdb/apps/entity_transform/__init__.py
wwpdb/apps/entity_transform/depict/DepictBase.py
wwpdb/apps/entity_transform/depict/LinkDepict.py
wwpdb/apps/entity_transform/depict/PrdSummaryDepict.py
wwpdb/apps/entity_transform/depict/ProcessPrdSummary.py
wwpdb/apps/entity_transform/depict/ProcessSummary_main.py
wwpdb/apps/entity_transform/depict/ResultDepict.py
wwpdb/apps/entity_transform/depict/SeqDepict.py
wwpdb/apps/entity_transform/depict/StrFormDepict.py
wwpdb/apps/entity_transform/depict/StrSummaryDepict.py
wwpdb/apps/entity_transform/depict/__init__.py
wwpdb/apps/entity_transform/openeye_util/OpenEyeUtil.py
wwpdb/apps/entity_transform/openeye_util/__init__.py
wwpdb/apps/entity_transform/prd/BuildPrd.py
wwpdb/apps/entity_transform/prd/BuildPrdUtil.py
wwpdb/apps/entity_transform/prd/CVSCommit.py
wwpdb/apps/entity_transform/prd/DepictPrd.py
wwpdb/apps/entity_transform/prd/DepictUtil.py
wwpdb/apps/entity_transform/prd/HtmlUtil.py
wwpdb/apps/entity_transform/prd/ReadFormUtil.py
wwpdb/apps/entity_transform/prd/UpdatePrd.py
wwpdb/apps/entity_transform/prd/__init__.py
wwpdb/apps/entity_transform/update/ChopperHandler.py
wwpdb/apps/entity_transform/update/CombineCoord.py
wwpdb/apps/entity_transform/update/EditPolymer.py
wwpdb/apps/entity_transform/update/MergeLigand.py
wwpdb/apps/entity_transform/update/MergePolymer.py
wwpdb/apps/entity_transform/update/SplitPolymer.py
wwpdb/apps/entity_transform/update/UpdateBase.py
wwpdb/apps/entity_transform/update/UpdateFile.py
wwpdb/apps/entity_transform/update/__init__.py
wwpdb/apps/entity_transform/utils/CommandUtil.py
wwpdb/apps/entity_transform/utils/CompUtil.py
wwpdb/apps/entity_transform/utils/DownloadFile.py
wwpdb/apps/entity_transform/utils/GetLogMessage.py
wwpdb/apps/entity_transform/utils/ImageGenerator.py
wwpdb/apps/entity_transform/utils/LinkUtil.py
wwpdb/apps/entity_transform/utils/RemoveEmptyCategories.py
