Metadata-Version: 2.4
Name: wwpdb.apps.entity_transform
Version: 0.21.4
Summary: wwPDB entity transformer
Home-page: https://github.com/rcsb/py-wwpdb_apps_entity_transform
Author: Ezra Peisach
Author-email: ezra.peisach@rcsb.org
License: Apache 2.0
Classifier: Development Status :: 3 - Alpha
Classifier: Intended Audience :: Developers
Classifier: Natural Language :: English
Classifier: License :: OSI Approved :: Apache Software License
Classifier: Programming Language :: Python
Classifier: Programming Language :: Python :: 2.7
Classifier: Programming Language :: Python :: 3
Classifier: Programming Language :: Python :: 3.6
Classifier: Programming Language :: Python :: 3.7
Requires-Dist: wwpdb.utils.config>=0.34
Requires-Dist: wwpdb.apps.editormodule>=0.13.1
Requires-Dist: wwpdb.io
Requires-Dist: wwpdb.utils.dp
Requires-Dist: wwpdb.utils.detach
Requires-Dist: wwpdb.utils.session
Requires-Dist: wwpdb.utils.wf
Requires-Dist: wwpdb.utils.oe_util
Provides-Extra: dev
Requires-Dist: check-manifest; extra == "dev"
Provides-Extra: test
Requires-Dist: coverage; extra == "test"
Dynamic: author
Dynamic: author-email
Dynamic: classifier
Dynamic: description
Dynamic: home-page
Dynamic: license
Dynamic: provides-extra
Dynamic: requires-dist
Dynamic: summary
